dataclass_baseclass.py
dataclass_baseclass-0.1.6.dist-info/METADATA
dataclass_baseclass-0.1.6.dist-info/WHEEL
dataclass_baseclass-0.1.6.dist-info/licenses/LICENSE
dataclass_baseclass-0.1.6.dist-info/RECORD
