Metadata-Version: 2.4
Name: dataclass-baseclass
Version: 0.1.6
Summary: Less verbose dataclasses
Project-URL: Homepage, https://codeberg.org/sledge/dataclass-baseclass
Project-URL: Issues, https://codeberg.org/sledge/dataclass-baseclass/issues
Author-email: Srdjan Janković <sledge@djenka.net>
License-File: LICENSE
Classifier: Development Status :: 4 - Beta
Classifier: License :: OSI Approved :: Artistic License
Classifier: Operating System :: OS Independent
Classifier: Programming Language :: Python :: 3
Requires-Python: >=3.11
